marvel_var/__init__.py
marvel_var/characters_fns.py
marvel_var-0.1.dist-info/LICENSE.txt
marvel_var-0.1.dist-info/METADATA
marvel_var-0.1.dist-info/WHEEL
marvel_var-0.1.dist-info/top_level.txt
marvel_var-0.1.dist-info/RECORD
